Workbook

Sheet Avance Financiero
A1: Cuenta Número 10000892 (Informe ejecución y rendimientos)
A2: Cuenta ahorros | B2: Fecha | C2: (+) Depositos (Gobernación de Antioquia) | D2: SALDO INICIAL | E2: (+) Rendimientos | F2: (-) Retiros por reintegro rendimientos | G2: (-) Ejecucion Convenio (Pagos Contrato Delegado) | I2: (-) Total Retiros | J2: SALDO FINAL
G3: Contigo Antioquia | H3: Otrosí - CRUE
A4: 100015699 | B4: 45594 | C4: 5000000000 | D4: 0 | E4: =+'EJecucion convenio 46000017482'!E60 -> 487902 | F4: 0 | G4: 0 | H4: 0 | I4: =SUM(F4:G4) -> 0 | J4: =D4+C4-I4+E4 -> 5000487902
A5: 100015699 | B5: 45626 | C5: 0 | D5: =J4 -> 5000487902 | E5: =+'EJecucion convenio 46000017482'!E61 -> 7277516 | F5: 0 | G5: 0 | H5: 0 | I5: =SUM(F5:G5) -> 0 | J5: =D5+C5-I5+E5 -> 5007765418
A6: 100015700 | B6: 45626 | C6: 0 | D6: =J5 -> 5007765418 | E6: =+'EJecucion convenio 46000017482'!E62 -> 5486 | F6: 0 | G6: 0 | H6: 0 | I6: =SUM(F6:G6) -> 0 | J6: =D6+C6-I6+E6 -> 5007770904
A7: 100015699 | B7: 45657 | C7: 0 | D7: =J6 -> 5007770904 | E7: =+'EJecucion convenio 46000017482'!E63 -> 7417358 | F7: 0 | G7: 0 | H7: 0 | I7: =SUM(F7:G7) -> 0 | J7: =D7+C7-I7+E7 -> 5015188262
A8: 100015700 | B8: 45657 | C8: 0 | D8: =J7 -> 5015188262 | E8: =+'EJecucion convenio 46000017482'!E64 -> 16571 | F8: 0 | G8: 0 | H8: 0 | I8: =SUM(F8:G8) -> 0 | J8: =D8+C8-I8+E8 -> 5015204833
A9: 100015699 | B9: 45688 | C9: 0 | D9: =J8 -> 5015204833 | E9: =+'EJecucion convenio 46000017482'!E65 -> 7422793 | F9: 0 | G9: 0 | H9: 0 | I9: =SUM(F9:G9) -> 0 | J9: =D9+C9-I9+E9 -> 5022627626
A10: 100015700 | B10: 45688 | C10: 0 | D10: =J9 -> 5022627626 | E10: =+'EJecucion convenio 46000017482'!E66 -> 27625 | F10: 0 | G10: 0 | H10: 0 | I10: =SUM(F10:G10) -> 0 | J10: =D10+C10-I10+E10 -> 5022655251
A11: 100015699 | B11: 45716 | C11: 0 | D11: =J10 -> 5022655251 | E11: =+'EJecucion convenio 46000017482'!E67 -> 6722333 | F11: 0 | G11: 0 | H11: 0 | I11: 0 | J11: =D11+C11-I11+E11 -> 5029377584
A12: 100015700 | B12: 45716 | C12: 0 | D12: =J11 -> 5029377584 | E12: =+'EJecucion convenio 46000017482'!E68 -> 34605 | F12: 0 | G12: 0 | H12: 0 | I12: =SUM(F12:G12) -> 0 | J12: =D12+C12-I12+E12 -> 5029412189
A13: 100015699 | B13: 45747 | C13: 0 | D13: =J12 -> 5029412189 | E13: =+'EJecucion convenio 46000017482'!E69 -> 7460534 | F13: 0 | G13: 0 | H13: 0 | I13: =SUM(F13:G13) -> 0 | J13: =D13+C13-I13+E13 -> 5036872723
A14: 100015700 | B14: 45747 | C14: 0 | D14: =J13 -> 5036872723 | E14: =+'EJecucion convenio 46000017482'!E70 -> 48968 | F14: 0 | G14: 0 | H14: 0 | I14: =SUM(F14:G14) -> 0 | J14: =D14+C14-I14+E14 -> 5036921691
A15: 100015699 | B15: 31/04/2025 | C15: 0 | D15: =J14 -> 5036921691 | E15: =+'EJecucion convenio 46000017482'!E71 -> 7156542 | F15: 0 | G15: 0 | H15: 0 | I15: =SUM(F15:G15) -> 0 | J15: =D15+C15-I15+E15 -> 5044078233
A16: 100015700 | B16: 31/04/2025 | C16: 0 | D16: =J15 -> 5044078233 | E16: =+'EJecucion convenio 46000017482'!E72 -> 57503 | F16: 0 | G16: 0 | H16: 0 | I16: =SUM(F16:G16) -> 0 | J16: =D16+C16-I16+E16 -> 5044135736
A17: 100015699 100015700 | B17: 45807 | C17: 0 | D17: =J16 -> 5044135736 | E17: 0 | F17: =+'EJecucion convenio 46000017482'!E122 -> 44135736 | G17: 0 | H17: 0 | I17: =SUM(F17:G17) -> 44135736 | J17: =D17+C17-I17+E17 -> 5000000000
A18: 100015699 | B18: 45808 | C18: 0 | D18: =J17 -> 5000000000 | E18: =+'EJecucion convenio 46000017482'!E73 -> 7274207 | F18: 0 | G18: 0 | H18: 0 | I18: =SUM(F18:G18) -> 0 | J18: =D18+C18-I18+E18 -> 5007274207
A19: 100015700 | B19: 45808 | C19: 0 | D19: =J18 -> 5007274207 | E19: =+'EJecucion convenio 46000017482'!E74 -> 62943 | F19: 0 | G19: 0 | H19: 0 | I19: =SUM(F19:G19) -> 0 | J19: =D19+C19-I19+E19 -> 5007337150
A20: 100015699 100015700 | B20: 45820 | C20: 0 | D20: =J19 -> 5007337150 | E20: 0 | F20: 7337150 | G20: 0 | H20: 0 | I20: =SUM(F20:G20) -> 7337150 | J20: =D20+C20-I20+E20 -> 5000000000
A21: 100015699 | B21: 45838 | C21: 0 | D21: =J20 -> 5000000000 | E21: =+'EJecucion convenio 46000017482'!E75 -> 6955975 | F21: 0 | G21: 0 | H21: 0 | I21: =SUM(F21:G21) -> 0 | J21: =D21+C21-I21+E21 -> 5006955975
A22: 100015700 | B22: 45838 | C22: 0 | D22: =J21 -> 5006955975 | E22: =+'EJecucion convenio 46000017482'!E76 -> 7390 | F22: 0 | G22: 0 | H22: 0 | I22: =SUM(F22:G22) -> 0 | J22: =D22+C22-I22+E22 -> 5006963365
A23: 100015699 100015700 | B23: 45861 | C23: 0 | D23: =J22 -> 5006963365 | E23: 0 | F23: =+'EJecucion convenio 46000017482'!E124 -> 6963365 | G23: 0 | H23: 0 | I23: =SUM(F23:G23) -> 6963365 | J23: =D23+C23-I23+E23 -> 5000000000
A24: 100015699 | B24: 45869 | C24: 0 | D24: =J23 -> 5000000000 | E24: =+'EJecucion convenio 46000017482'!E77 -> 7212374 | F24: 0 | G24: 0 | H24: 0 | I24: =SUM(F24:G24) -> 0 | J24: =D24+C24-I24+E24 -> 5007212374
A25: 100015700 | B25: 45869 | C25: 0 | D25: =J24 -> 5007212374 | E25: =+'EJecucion convenio 46000017482'!E78 -> 11633 | F25: 0 | G25: 0 | H25: 0 | I25: =SUM(F25:G25) -> 0 | J25: =D25+C25-I25+E25 -> 5007224007
A26: 100015699 | B26: 45881 | C26: 0 | D26: =J25 -> 5007224007 | E26: 0 | F26: 0 | G26: 2200000000 | H26: 0 | I26: =SUM(F26:G26) -> 2200000000 | J26: =D26+C26-I26+E26 -> 2807224007
A27: 100015699 100015700 | B27: 45884 | C27: 0 | D27: =J26 -> 2807224007 | E27: 0 | F27: 7224007 | G27: 0 | H27: 0 | I27: =SUM(F27:G27) -> 7224007 | J27: =D27+C27-I27+E27 -> 2800000000
A28: =+'EJecucion convenio 46000017482'!A79 -> 100015699 | B28: =IF('EJecucion convenio 46000017482'!C79="","",'EJecucion convenio 46000017482'!C79) -> 45900 | C28: 0 | D28: =J27 -> 2800000000 | E28: =+'EJecucion convenio 46000017482'!E79 -> 6016060 | F28: 0 | G28: 0 | H28: 0 | I28: =SUM(F28:G28) -> 0 | J28: =D28+C28-I28+E28 -> 2806016060
A29: =+'EJecucion convenio 46000017482'!A80 -> 100015700 | B29: =IF('EJecucion convenio 46000017482'!C80="","",'EJecucion convenio 46000017482'!C80) -> 45900 | C29: 0 | D29: =J28 -> 2806016060 | E29: =+'EJecucion convenio 46000017482'!E80 -> 9042 | F29: 0 | G29: 0 | H29: 0 | I29: =SUM(F29:G29) -> 0 | J29: =D29+C29-I29+E29 -> 2806025102
A30: 100015699 100015700 | B30: 45922 | C30: 0 | D30: =J29 -> 2806025102 | E30: 0 | F30: 6025102 | G30: 0 | H30: 0 | I30: =SUM(F30:G30) -> 6025102 | J30: =D30+C30-I30+E30 -> 2800000000
A31: 100015699 | B31: 45925 | C31: 0 | D31: =J30 -> 2800000000 | E31: 0 | F31: 0 | G31: 998095000 | H31: 0 | I31: =SUM(F31:G31) -> 998095000 | J31: =D31+C31-I31+E31 -> 1801905000
A32: 100015699 | B32: 45925 | C32: 0 | D32: =J31 -> 1801905000 | E32: 0 | F32: 0 | G32: 190754739 | H32: 0 | I32: =SUM(F32:G32) -> 190754739 | J32: =D32+C32-I32+E32 -> 1611150261
A33: =+'EJecucion convenio 46000017482'!A81 -> 100015699 | B33: =IF('EJecucion convenio 46000017482'!C81="","",'EJecucion convenio 46000017482'!C81) -> 45930 | C33: 0 | D33: =J32 -> 1611150261 | E33: =+'EJecucion convenio 46000017482'!E81 -> 3507390 | F33: 0 | G33: 0 | H33: 0 | I33: =SUM(F33:G33) -> 0 | J33: =D33+C33-I33+E33 -> 1614657651
A34: =+'EJecucion convenio 46000017482'!A82 -> 100015700 | B34: =IF('EJecucion convenio 46000017482'!C82="","",'EJecucion convenio 46000017482'!C82) -> 45930 | C34: 0 | D34: =J33 -> 1614657651 | E34: =+'EJecucion convenio 46000017482'!E82 -> 7347 | F34: 0 | G34: 0 | H34: 0 | I34: =SUM(F34:G34) -> 0 | J34: =D34+C34-I34+E34 -> 1614664998
A35: 100015699 100015700 | B35: 45937 | C35: 0 | D35: =J34 -> 1614664998 | E35: 0 | F35: 3514737 | G35: 0 | H35: 0 | I35: =SUM(F35:G35) -> 3514737 | J35: =D35+C35-I35+E35 -> 1611150261
A36: 100015699 | B36: 45954 | C36: 0 | D36: =J35 -> 1611150261 | E36: 0 | F36: 0 | G36: 13650000 | H36: 0 | I36: =SUM(F36:G36) -> 13650000 | J36: =D36+C36-I36+E36 -> 1597500261
A37: 100015699 | B37: 45954 | C37: 0 | D37: =J36 -> 1597500261 | E37: 0 | F37: 0 | G37: 95018644 | H37: 0 | I37: =SUM(F37:G37) -> 95018644 | J37: =D37+C37-I37+E37 -> 1502481617
A38: 100015699 | B38: 45954 | C38: 0 | D38: =J37 -> 1502481617 | E38: =+'EJecucion convenio 46000017482'!E93 -> 281635 | F38: 0 | G38: 730635725 | H38: 0 | I38: =SUM(F38:G38) -> 730635725 | J38: =D38+C38-I38+E38 -> 772127527
A39: 100015699 | B39: 45954 | C39: 0 | D39: =J38 -> 772127527 | E39: =+'EJecucion convenio 46000017482'!E94 -> 5510 | F39: 0 | G39: 211478886 | H39: 0 | I39: =SUM(F39:G39) -> 211478886 | J39: =D39+C39-I39+E39 -> 560654151
A40: =+'EJecucion convenio 46000017482'!A88 -> 100015700 | B40: 45961 | C40: 0 | D40: =J39 -> 560654151 | E40: 2120535 | F40: 0 | H40: 0 | I40: =SUM(F40:G40) -> 0 | J40: =D40+C40-I40+E40 -> 562774686
A41: =+'EJecucion convenio 46000017482'!A89 -> 100015716 | B41: 45961 | C41: 0 | D41: =J40 -> 562774686 | E41: 2412 | F41: 0 | G41: 0 | H41: 0 | I41: =SUM(F41:G41) -> 0 | J41: =D41+C41-I41+E41 -> 562777098
A42: =+'EJecucion convenio 46000017482'!A90 -> 100015699 | B42: 45965 | C42: 0 | D42: =J41 -> 562777098 | E42: 637896 | F42: 0 | G42: 0 | H42: 0 | I42: 0 | J42: =D42+C42-I42+E42 -> 563414994
A43: =+'EJecucion convenio 46000017482'!A91 -> 100015700 | B43: 45965 | C43: 0 | D43: =J42 -> 563414994 | E43: 2080 | F43: 0 | G43: 0 | H43: 0 | I43: 0 | J43: =D43+C43-I43+E43 -> 563417074
A44: 100015699 100015700 | B44: 45979 | C44: 0 | D44: =J43 -> 563417074 | E44: 0 | F44: 2122947 | G44: 0 | H44: 0 | I44: =SUM(F44:G44) -> 2122947 | J44: =D44+C44-I44+E44 -> 561294127
A45: 100015699 | B45: 45986 | C45: 0 | D45: =J44 -> 561294127 | E45: 0 | F45: 0 | G45: 70856001 | H45: 0 | I45: =SUM(F45:G45) -> 70856001 | J45: =D45+C45-I45+E45 -> 490438126
A46: 100015699 | B46: 45986 | C46: 0 | D46: =J45 -> 490438126 | E46: 0 | F46: 0 | G46: 364100919 | H46: 0 | I46: =SUM(F46:G46) -> 364100919 | J46: =D46+C46-I46+E46 -> 126337207
A47: 100015699 | B47: 45986 | C47: 0 | D47: =J46 -> 126337207 | E47: 0 | F47: 0 | G47: 13650000 | H47: 0 | I47: =SUM(F47:G47) -> 13650000 | J47: =D47+C47-I47+E47 -> 112687207
B48: 46001 | C48: 6000000000 | D48: =J47 -> 112687207 | E48: 0 | F48: 0 | G48: 0 | H48: 0 | I48: =SUM(F48:G48) -> 0 | J48: =D48+C48-I48+E48 -> 6112687207
B49: 46007 | C49: 0 | D49: =J48 -> 6112687207 | E49: 0 | F49: 0 | G49: 13650000 | H49: 0 | I49: =SUM(F49:G49) -> 13650000 | J49: =D49+C49-I49+E49 -> 6099037207
B50: 46007 | C50: 0 | D50: =J49 -> 6099037207 | E50: 0 | F50: 0 | G50: 1095953586 | H50: 0 | I50: =SUM(F50:G50) -> 1095953586 | J50: =D50+C50-I50+E50 -> 5003083621
B51: 46007 | C51: 0 | D51: =J50 -> 5003083621 | E51: 0 | F51: 0 | G51: 1299480 | H51: 0 | I51: =SUM(F51:G51) -> 1299480 | J51: =D51+C51-I51+E51 -> 5001784141
B52: 46007 | C52: 0 | D52: =J51 -> 5001784141 | E52: 0 | F52: 0 | G52: 262400529 | H52: 0 | I52: =SUM(F52:G52) -> 262400529 | J52: =D52+C52-I52+E52 -> 4739383612
B53: 46048 | C53: 0 | D53: =J52 -> 4739383612 | E53: 0 | F53: 0 | G53: 1539588229 | H53: 0 | I53: =SUM(F53:G53) -> 1539588229 | J53: =D53+C53-I53+E53 -> 3199795383
B54: 46048 | C54: 0 | D54: =J53 -> 3199795383 | E54: 0 | F54: 0 | G54: 105634262 | H54: 0 | I54: =SUM(F54:G54) -> 105634262 | J54: =D54+C54-I54+E54 -> 3094161121
B55: 46048 | C55: 0 | D55: =J54 -> 3094161121 | E55: 0 | F55: 0 | G55: 378854365 | H55: 0 | I55: =SUM(F55:G55) -> 378854365 | J55: =D55+C55-I55+E55 -> 2715306756
B56: 46048 | C56: 0 | D56: =J55 -> 2715306756 | E56: 0 | F56: 0 | G56: 13650000 | H56: 0 | I56: =SUM(F56:G56) -> 13650000 | J56: =D56+C56-I56+E56 -> 2701656756
B57: 10/02/2026 | C57: 0 | D57: =J56 -> 2701656756 | E57: 0 | F57: 0 | G57: 0 | H57: 0 | I57: =SUM(F57:G57) -> 0 | J57: =D57+C57-I57+E57 -> 2701656756
B58: 10/02/2026 | C58: 0 | D58: =J57 -> 2701656756 | E58: 0 | F58: 0 | G58: 0 | H58: 0 | I58: =SUM(F58:G58) -> 0 | J58: =D58+C58-I58+E58 -> 2701656756
B59: 10/02/2026 | C59: 0 | D59: =J58 -> 2701656756 | E59: 0 | F59: 0 | G59: 0 | H59: 0 | I59: =SUM(F59:G59) -> 0 | J59: =D59+C59-I59+E59 -> 2701656756
C60: 0 | D60: =J59 -> 2701656756 | E60: 0 | F60: 0 | G60: 0 | H60: 0 | I60: =SUM(F60:G60) -> 0 | J60: =D60+C60-I60+E60 -> 2701656756
C61: 0 | D61: =J60 -> 2701656756 | E61: 0 | F61: 0 | G61: 0 | H61: 0 | I61: =SUM(F61:G61) -> 0 | J61: =D61+C61-I61+E61 -> 2701656756
C62: 0 | D62: =J61 -> 2701656756 | E62: 0 | F62: 0 | G62: 0 | H62: 0 | I62: =SUM(F62:G62) -> 0 | J62: =D62+C62-I62+E62 -> 2701656756
C63: 0 | D63: =J62 -> 2701656756 | E63: 0 | F63: 0 | G63: 0 | H63: 0 | I63: =SUM(F63:G63) -> 0 | J63: =D63+C63-I63+E63 -> 2701656756
C64: 0 | D64: =J63 -> 2701656756 | E64: 0 | F64: 0 | G64: 0 | H64: 0 | I64: =SUM(F64:G64) -> 0 | J64: =D64+C64-I64+E64 -> 2701656756
C65: 0 | D65: =J64 -> 2701656756 | E65: 0 | F65: 0 | G65: 0 | H65: 0 | I65: =SUM(F65:G65) -> 0 | J65: =D65+C65-I65+E65 -> 2701656756
C66: 0 | D66: =J65 -> 2701656756 | E66: 0 | F66: 0 | G66: 0 | H66: 0 | I66: =SUM(F66:G66) -> 0 | J66: =D66+C66-I66+E66 -> 2701656756
C67: 0 | D67: =J66 -> 2701656756 | E67: 0 | F67: 0 | G67: 0 | H67: 0 | I67: =SUM(F67:G67) -> 0 | J67: =D67+C67-I67+E67 -> 2701656756
C68: 0 | D68: =J67 -> 2701656756 | E68: 0 | F68: 0 | G68: 0 | H68: 0 | I68: =SUM(F68:G68) -> 0 | J68: =D68+C68-I68+E68 -> 2701656756
C69: 0 | D69: =J68 -> 2701656756 | E69: 0 | F69: 0 | G69: 0 | H69: 0 | I69: =SUM(F69:G69) -> 0 | J69: =D69+C69-I69+E69 -> 2701656756
C70: 0 | D70: =J69 -> 2701656756 | E70: 0 | F70: 0 | G70: 0 | H70: 0 | I70: =SUM(F70:G70) -> 0 | J70: =D70+C70-I70+E70 -> 2701656756
C71: 0 | D71: =J70 -> 2701656756 | E71: 0 | F71: 0 | G71: 0 | H71: 0 | I71: =SUM(F71:G71) -> 0 | J71: =D71+C71-I71+E71 -> 2701656756
... C142: 0 | D142: =J141 -> 2701656756 | E142: 0 | F142: 0 | G142: 0 | H142: 0 | I142: =SUM(F142:G142) -> 0 | J142: =D142+C142-I142+E142 -> 2701656756
A143: TOTALES | C143: =SUM(C4:C142) -> 11000000000 | E143: =SUM(E4:E142) -> 78250165 | F143: =SUM(F4:F142) -> 77323044 | G143: =SUM(G4:G142) -> 8299270365 | H143: =SUM(H4:H142) -> 0 | I143: =SUM(I4:I142) -> 8376593409 | J143: =+C143+E143-F143-G143-H143 -> 2701656756

Sheet EJecucion convenio 46000017482
A2: Convenio: 4600017482/0231 de 2024
A3: Objeto: | B3: "Aunar esfuerzos en la constitución de un fondo especial de recursos, para Implementar estrategias para la transformación digital en el Departamento de Antioquia – Secretaría Seccional de Salud y Protección Social."
A4: Fecha de Suscripcion: | B4: 45582 | C4: Fecha de Inicio: | D4: 45589
A5: Plazo: | B5: Meses | C5: 39 | D5: Días | E5: =+C5*30 -> 1170
A6: Fecha de Terminación: | B6: 46752
A7: Otrosí 1: | B7: 46020
A8: Adición de recursos: | B8: 1462022598
A9: Disponibilidad Presupuestal
A10: FECHA CREACIÓN | B10: VIGENCIA | C10: VALOR | D10: RESPALDO PRESUPUESTAL
A11: 44918 | B11: 2024 | C11: 5000000000 | D11: CDP 3500054749
A12: 44918 | B12: 2025 | C12: 1500000000 | D12: Certificado de vigencia futura No. 6000003088
A13: 44918 | B13: 2025 | C13: 1500000000 | D13: Certificado de vigencia futura No. 6000003093
A14: 44918 | B14: 2025 | C14: 1500000000 | D14: Certificado de vigencia futura No. 6000003098
A15: 44918 | B15: 2025 | C15: 1500000000 | D15: Certificado de vigencia futura No. 6000003103
A16: 44918 | B16: 2026 | C16: 1750000000 | D16: Certificado de vigencia futura No. 6000003089
A17: 44918 | B17: 2026 | C17: 1750000000 | D17: Certificado de vigencia futura No. 6000003094
A18: 44918 | B18: 2026 | C18: 1750000000 | D18: Certificado de vigencia futura No. 6000003099
A19: 44918 | B19: 2026 | C19: 1750000000 | D19: Certificado de vigencia futura No. 6000003104 | K19: 27568325
A20: 44918 | B20: 2027 | C20: 2000000000 | D20: Certificado de vigencia futura No. 6000003090 | K20: 16130869
A21: 44918 | B21: 2027 | C21: 2000000000 | D21: Certificado de vigencia futura No. 6000003095 | K21: 4358895
A22: 44918 | B22: 2027 | C22: 2000000000 | D22: Certificado de vigencia futura No. 6000003100 | K22: 45786710
A23: 44918 | B23: 2027 | C23: 2000000000 | D23: Certificado de vigencia futura No. 6000003105 | K23: 48935567
J24: 207173258 | K24: =SUM(K19:K23) -> 142780366 | L24: =+J24-K24 -> 64392892
A27: Supervisor: | B27: David Fernando Arisitizábal Serna | D27: Identificación | E27: 71740628
A28: Dependencia: | B28: Secretaría de Salud e Inclusión Social | D28: Fuente de Financiación: | E28: Transformación Digital en Salud
A29: Encargo fiduciario | B29: 10000892
B30: Cuenta encargo | C30: 100015699 | D30: Cuenta rendimientos | E30: 100015700
A31: Banco: | B31: IDEA | D31: Estado cuenta: | E31: Activa
A33: VALOR CONVENIO
A34: Aportantes | B34: Aportes totales | C34: Gobernación de Antioquia Secretaría de Salud e Inclusión social | D34: IDEA Costos operativos (Aportes en especie)
A35: Aporte total | B35: =+C35+D35 -> 27300000000 | C35: 26000000000 | D35: 1300000000
A36: Totales % | B36: =C36+D36 -> 1 | C36: =+C35/$B$35 -> 0.95238095 | D36: =+D35/$B$35 -> 0.047619048
A37: Aporte total (recursos liquidos) | B37: =+C35 -> 26000000000 | C37: =SUM(C34:C35) -> 26000000000 | D37: =SUM(D34:D35) -> 1300000000
A38: Subtotales % | B38: =C38+D38 -> 1 | C38: =+C37/B35 -> 0.95238095 | D38: =+D37/$B$35 -> 0.047619048
A39: TOTAL VALOR DEL CONVENIO | B39: =+C35+D35 -> 27300000000
A41: APORTES REALIZADOS
A42: Documento - Fecha | B42: Fecha de Consiganción | C42: Valor | D42: Gobernación de Antioquia Secretaría de Salud e Inclusión social | E42: IDEA Costos operativos (Aportes en especie)
A43: 4300126000 | B43: 45594 | C43: 5000000000 | D43: =+C43 -> 5000000000 | E43: 0
A44: Acta de inicio 24/10/2024 | B44: 45594 | C44: 1300000000 | D44: 0 | E44: =+C44 -> 1300000000
A45: 4300131771 | B45: 46007 | C45: 6000000000 | D45: =+C45 -> 6000000000 | E45: 0
A46: Otrosí No. 1 | B46: 46020 | C46: 73101130 | D46: 0 | E46: =+C46 -> 73101130
A47: 4300132327 | B47: 46044 | C47: 207173258 | D47: =+C47 -> 207173258 | E47: 0
A48: 4300132899 | B48: 46107 | C48: 608644587 | D48: =+C48 -> 608644587 | E48: 0
C49: 7000000000 | D49: =+C49 -> 7000000000
D50: =+C50 -> 0
E52: 0
E53: 0
D54: =+C54 -> 0 | E54: 0
A55: TOTALES | C55: =SUM(C43:C54) -> 20188918975 | D55: =SUM(D43:D54) -> 18815817845 | E55: =SUM(E43:E54) -> 1373101130
A58: RENDIMIENTOS FINANCIEROS
A59: Cuenta ahorros | B59: Periodo Rendimiento | D59: Valor | E59: Gobernación de Antioquia Secretaría de Salud e Inclusión social
A60: 100015699 | B60: 45594 | C60: 45596 | D60: 487902 | E60: =D60 -> 487902
A61: 100015699 | B61: 45597 | C61: 45626 | D61: 7277516 | E61: =D61 -> 7277516
A62: 100015700 | B62: 45597 | C62: 45626 | D62: 5486 | E62: =D62 -> 5486
A63: 100015699 | B63: 45627 | C63: 45657 | D63: 7417358 | E63: =D63 -> 7417358
A64: 100015700 | B64: 45627 | C64: 45657 | D64: 16571 | E64: =D64 -> 16571
A65: 100015699 | B65: 45658 | C65: 45688 | D65: 7422793 | E65: =D65 -> 7422793
A66: 100015700 | B66: 45658 | C66: 45688 | D66: 27625 | E66: =D66 -> 27625
A67: 100015699 | B67: 45689 | C67: 45716 | D67: 6722333 | E67: =D67 -> 6722333
A68: 100015700 | B68: 45689 | C68: 45716 | D68: 34605 | E68: =D68 -> 34605
A69: 100015699 | B69: 45717 | C69: 45747 | D69: 7460534 | E69: =D69 -> 7460534
A70: 100015700 | B70: 45717 | C70: 45747 | D70: 48968 | E70: =D70 -> 48968
A71: 100015699 | B71: 45748 | C71: 31/04/2025 | D71: 7156542 | E71: =D71 -> 7156542
A72: 100015700 | B72: 45748 | C72: 31/04/2025 | D72: 57503 | E72: =D72 -> 57503
A73: 100015699 | B73: 45778 | C73: 45808 | D73: 7274207 | E73: =D73 -> 7274207
A74: 100015700 | B74: 45778 | C74: 45808 | D74: 62943 | E74: =D74 -> 62943
A75: 100015699 | B75: 45809 | C75: 45838 | D75: 6955975 | E75: =D75 -> 6955975
A76: 100015700 | B76: 45809 | C76: 45838 | D76: 7390 | E76: =D76 -> 7390
A77: 100015699 | B77: 45839 | C77: 45869 | D77: 7212374 | E77: =D77 -> 7212374
A78: 100015700 | B78: 45839 | C78: 45869 | D78: 11633 | E78: =D78 -> 11633
A79: 100015699 | B79: 45870 | C79: 45900 | D79: 6016060 | E79: =D79 -> 6016060
A80: 100015700 | B80: 45870 | C80: 45900 | D80: 9042 | E80: =D80 -> 9042
A81: 100015699 | B81: 45901 | C81: 45930 | D81: 3507390 | E81: =D81 -> 3507390
A82: 100015700 | B82: 45901 | C82: 45930 | D82: 7347 | E82: =D82 -> 7347
A83: 100015699 | B83: 45931 | C83: 45961 | D83: 2120535 | E83: =D83 -> 2120535
A84: 100015700 | B84: 45931 | C84: 45961 | D84: 2412 | E84: =D84 -> 2412
... A104: 100015716 | B104: 46143 | C104: 46173 | D104: 754773 | E104: =D104 -> 754773
A105: 100015699 | B105: 46174 | C105: 31/6/2026 | D105: 249769 | E105: =D105 -> 249769
A106: 100015700 | B106: 46174 | C106: 31/6/2026 | D106: 4232 | E106: =D106 -> 4232
A107: 100015716 | B107: 46174 | C107: 31/6/2026 | D107: 726486 | E107: =D107 -> 726486
A108: 100015699 | B108: 46204 | C108: 46234 | D108: 87567 | E108: =D108 -> 87567
A109: 100015700 | B109: 46204 | C109: 46234 | D109: 1334 | E109: =D109 -> 1334
A110: 100015716 | B110: 46204 | C110: 46234 | D110: 754686 | E110: =D110 -> 754686
E111: =D111 -> 0
E112: =D112 -> 0
E113: =D113 -> 0
A114: TOTALES | D114: =SUM(D60:D113) -> 100449902 | E114: =SUM(E60:E113) -> 100449902
A116: TOTAL POR CUENTA | C116: Cuenta ahorros 100015699 | E116: =SUMIF(A60:A113,100015699,E60:E113) -> 79979884
C117: Cuenta ahorros 100015700 | E117: =SUMIF(A60:A113,100015700,E60:E113) -> 329755
C118: Cuenta ahorros 100015716 | E118: =SUMIF(A61:A113,100015716,E61:E113) -> 20140263
A120: REINTEGRO RENDIMIENTOS FINANCIEROS
A121: # Reintegro Rendimientos | B121: Soporte | C121: Fecha | D121: Valor | E121: Gobernación de Antioquia Secretaría de Salud e Inclusión social
A122: Reintegro Nro. 01 | B122: 1000229137 | C122: 45807 | D122: 44135736 | E122: =D122 -> 44135736
A123: Reintegro Nro. 02 | B123: 1000229324 | C123: 45820 | D123: 7337150 | E123: =D123 -> 7337150
A124: Reintegro Nro. 03 | B124: 1000230117 | C124: 45861 | D124: 6963365 | E124: =D124 -> 6963365
A125: Reintegro Nro. 04 | B125: 1000232704 | C125: 45884 | D125: 7224007 | E125: =D125 -> 7224007
A126: Reintegro Nro. 05 | B126: 1000234286 | C126: 45922 | D126: 6025102 | E126: =D126 -> 6025102
A127: Reintegro Nro. 06 | B127: 1000234743 | C127: 45937 | D127: 3514737 | E127: =D127 -> 3514737
A128: Reintegro Nro. 07 | B128: 1000236760 | C128: 45979 | D128: 2122947 | E128: =D128 -> 2122947
A129: Reintegro Nro. 08 | B129: 1000237544 | C129: 46030 | D129: 639976 | E129: =D129 -> 639976
...

Sheet Ejecución financiera CAS
B1: Ejecución Recursos Contigo Antioquia: Secrataría de Salud e Inclusión Social
B2: Fecha | C2: Componente | F2: Recursos comprometidos | O2: =+O9+O10+O11+O12+7000000000 -> 18815817845
B3: 45757 | C3: Contigo Antioquia Salud - CAS | F3: 25982939387 | O3: =+O2+O36 -> 20188918975
B4: 46020 | C4: Contigo Antioquia Salud - CRUE | F4: 1462022598
B7: Valor Total Contrato | F7: =SUM(F3:G4) -> 27444961985 | I7: Ejecución de Recursos Transferidos al IDEA | N7: Recursos Transferidos al IDEA
B8: Componente | C8: Fecha | D8: Soporte | E8: Ejecución Financiera Valor + | G8: Sin ejecución | I8: Fecha | J8: Ejecución Financiera Valor + | L8: Sin ejecución | N8: Fecha | O8: Valor Transferido IDEA | Q8: Componente
A9: =IF(C9="","",ROW()-8) -> 1 | B9: CAS | C9: 12/08/2025 | D9: Factura V1460 | E9: 2200000000 | F9: =+SUM(E9:E75)/$F$7 -> 0.54312004 | G9: =IF(E9=0,0,F3-E9) -> 23782939387 | I9: =IF(C9="","",+C9) -> 12/08/2025 | J9: =+E9 -> 2200000000 | K9: =SUM(J9:J75)/O34 -> 0.96995397 | L9: =IF(J9=0,"",O34-J9) -> 13167645700 | N9: 45594 | O9: 5000000000 | P9: =+O34/F7 -> 0.55994414 | Q9: CAS
A10: =IF(C10="","",ROW()-8) -> 2 | B10: CAS | C10: 02/09/2025 | D10: Cuanta de Cobro 229 | E10: 998095000 | G10: =IF(E10=0,0,G9-E10) -> 22784844387 | I10: =IF(C10="","",+C10) -> 02/09/2025 | J10: =+E10 -> 998095000 | L10: =IF(J10=0,"",L9-J10) -> 12169550700 | N10: 46001 | O10: 6000000000 | Q10: CAS
A11: =IF(C11="","",ROW()-8) -> 3 | B11: CAS | C11: 16/09/2025 | D11: Factura V1519 | E11: 190754739 | G11: =IF(E11=0,0,G10-E11) -> 22594089648 | I11: =IF(C11="","",+C11) -> 16/09/2025 | J11: =+E11 -> 190754739 | L11: =IF(J11=0,"",L10-J11) -> 11978795961 | N11: 46044 | O11: 207173258 | Q11: CRUE | R11: 7000000000
A12: =IF(C12="","",ROW()-8) -> 4 | B12: CAS | C12: 23/10/2025 | D12: Cuanta de Cobro 259 | E12: 13650000 | G12: =IF(E12=0,0,G11-E12) -> 22580439648 | I12: =IF(C12="","",+C12) -> 23/10/2025 | J12: =+E12 -> 13650000 | L12: =IF(J12=0,"",L11-J12) -> 11965145961 | N12: 46101 | O12: 608644587 | Q12: CRUE
A13: =IF(C13="","",ROW()-8) -> 5 | B13: CAS | C13: 23/10/2025 | D13: Cuanta de Cobro 261 | E13: 95018644 | G13: =IF(E13=0,0,G12-E13) -> 22485421004 | I13: =IF(C13="","",+C13) -> 23/10/2025 | J13: =+E13 -> 95018644 | L13: =IF(J13=0,"",L12-J13) -> 11870127317 | N13: 46171 | O13: 1817086974 | Q13: CAS | R13: =SUM(O13:O20) -> 3551827855
A14: =IF(C14="","",ROW()-8) -> 6 | B14: CAS | C14: 23/10/2025 | D14: Factura V1554 | E14: 730635725 | G14: =IF(E14=0,0,G13-E14) -> 21754785279 | I14: =IF(C14="","",+C14) -> 23/10/2025 | J14: =+E14 -> 730635725 | L14: =IF(J14=0,"",L13-J14) -> 11139491592 | N14: 46191 | O14: 526978224 | Q14: CAS
A15: =IF(C15="","",ROW()-8) -> 7 | B15: CAS | C15: 23/10/2025 | D15: Factura V1561 | E15: 211478886 | G15: =IF(E15=0,0,G14-E15) -> 21543306393 | I15: =IF(C15="","",+C15) -> 23/10/2025 | J15: =+E15 -> 211478886 | L15: =IF(J15=0,"",L14-J15) -> 10928012706 | N15: 46220 | O15: 526978224 | Q15: CAS | R15: =+R11-R13 -> 3448172145
A16: =IF(C16="","",ROW()-8) -> 8 | B16: CAS | C16: 25/11/2025 | D16: Factura V1598 | E16: 70856001 | G16: =IF(E16=0,0,G15-E16) -> 21472450392 | I16: =IF(C16="","",+C16) -> 25/11/2025 | J16: =+E16 -> 70856001 | L16: =IF(J16=0,"",L15-J16) -> 10857156705 | O16: 680784433 | Q16: CAS
A17: =IF(C17="","",ROW()-8) -> 9 | B17: CAS | C17: 25/11/2025 | D17: Factura V1600 | E17: 364100919 | G17: =IF(E17=0,0,G16-E17) -> 21108349473 | I17: =IF(C17="","",+C17) -> 25/11/2025 | J17: =+E17 -> 364100919 | L17: =IF(J17=0,"",L16-J17) -> 10493055786
A18: =IF(C18="","",ROW()-8) -> 10 | B18: CAS | C18: 25/11/2025 | D18: Cuenta de Cobro 291 | E18: 13650000 | G18: =IF(E18=0,0,G17-E18) -> 21094699473 | I18: =IF(C18="","",+C18) -> 25/11/2025 | J18: =+E18 -> 13650000 | L18: =IF(J18=0,"",L17-J18) -> 10479405786 | R18: =+O13+O14 -> 2344065198
A19: =IF(C19="","",ROW()-8) -> 11 | B19: CAS | C19: 02/12/2025 | D19: Cuenta de Cobro 320 | E19: 13650000 | G19: =IF(E19=0,0,G18-E19) -> 21081049473 | I19: =IF(C19="","",+C19) -> 02/12/2025 | J19: =+E19 -> 13650000 | L19: =IF(J19=0,"",L18-J19) -> 10465755786 | R19: =+R11-R18 -> 4655934802
A20: =IF(C20="","",ROW()-8) -> 12 | B20: CAS | C20: 02/12/2025 | D20: Cuenta de Cobro 321 | E20: 1095953586 | G20: =IF(E20=0,0,G19-E20) -> 19985095887 | I20: =IF(C20="","",+C20) -> 02/12/2025 | J20: =+E20 -> 1095953586 | L20: =IF(J20=0,"",L19-J20) -> 9369802200 | R20: 4441000000
A21: =IF(C21="","",ROW()-8) -> 13 | B21: CAS | C21: 03/12/2025 | D21: Factura V1633 | E21: 1299480 | G21: =IF(E21=0,0,G20-E21) -> 19983796407 | I21: =IF(C21="","",+C21) -> 03/12/2025 | J21: =+E21 -> 1299480 | L21: =IF(J21=0,"",L20-J21) -> 9368502720 | R21: =+R19-R20 -> 214934802
A22: =IF(C22="","",ROW()-8) -> 14 | B22: CAS | C22: 03/12/2025 | D22: Factura V1634 | E22: 262400529 | G22: =IF(E22=0,0,G21-E22) -> 19721395878 | I22: =IF(C22="","",+C22) -> 03/12/2025 | J22: =+E22 -> 262400529 | L22: =IF(J22=0,"",L21-J22) -> 9106102191
A23: =IF(C23="","",ROW()-8) -> 15 | B23: CAS | C23: 16/01/2026 | D23: Cuenta de Cobro 378 | E23: 1539588229 | G23: =IF(E23=0,0,G22+F4-E23) -> 19643830247 | I23: =IF(C23="","",+C23) -> 16/01/2026 | J23: =+E23 -> 1539588229 | L23: =IF(J23=0,"",L22-J23) -> 7566513962
A24: =IF(C24="","",ROW()-8) -> 16 | B24: CAS | C24: 19/01/2026 | D24: Factura V1741 | E24: 105634262 | G24: =IF(E24=0,0,G23-E24) -> 19538195985 | I24: =IF(C24="","",+C24) -> 19/01/2026 | J24: =+E24 -> 105634262 | L24: =IF(J24=0,"",L23-J24) -> 7460879700
A25: =IF(C25="","",ROW()-8) -> 17 | B25: CAS | C25: 19/01/2026 | D25: Factura V1740 | E25: 378854365 | G25: =IF(E25=0,0,G24-E25) -> 19159341620 | I25: =IF(C25="","",+C25) -> 19/01/2026 | J25: =+E25 -> 378854365 | L25: =IF(J25=0,"",L24-J25) -> 7082025335
A26: =IF(C26="","",ROW()-8) -> 18 | B26: CAS | C26: 16/01/2026 | D26: Cuenta de cobro 377 | E26: 13650000 | G26: =IF(E26=0,0,G25-E26) -> 19145691620 | I26: =IF(C26="","",+C26) -> 16/01/2026 | J26: =+E26 -> 13650000 | L26: =IF(J26=0,"",L25-J26) -> 7068375335
A27: =IF(C27="","",ROW()-8) -> 19 | B27: CAS | C27: 10/02/2026 | D27: Factura V1756 | E27: 1157936725 | G27: =IF(E27=0,0,G26-E27) -> 17987754895 | I27: =IF(C27="","",+C27) -> 10/02/2026 | J27: =+E27 -> 1157936725 | L27: =IF(J27=0,"",L26-J27) -> 5910438610
A28: =IF(C28="","",ROW()-8) -> 20 | B28: CAS | C28: 10/02/2026 | D28: Factura V1757 | E28: 147868279 | G28: =IF(E28=0,0,G27-E28) -> 17839886616 | I28: =IF(C28="","",+C28) -> 10/02/2026 | J28: =+E28 -> 147868279 | L28: =IF(J28=0,"",L27-J28) -> 5762570331
A29: =IF(C29="","",ROW()-8) -> 21 | B29: CAS | C29: 10/02/2026 | D29: Cuenta de cobro 384 | E29: 13991250 | G29: =IF(E29=0,0,G28-E29) -> 17825895366 | I29: =IF(C29="","",+C29) -> 10/02/2026 | J29: =+E29 -> 13991250 | L29: =IF(J29=0,"",L28-J29) -> 5748579081
A30: =IF(C30="","",ROW()-8) -> 22 | B30: CAS | C30: 10/03/2026 | D30: Cuenta de cobro 400 | E30: 13991250 | G30: =IF(E30=0,0,G29-E30) -> 17811904116 | I30: =IF(C30="","",+C30) -> 10/03/2026 | J30: =+E30 -> 13991250 | L30: =IF(J30=0,"",L29-J30) -> 5734587831
A31: =IF(C31="","",ROW()-8) -> 23 | B31: CAS | C31: 11/03/2026 | D31: Factura V1808 | E31: 1331967 | G31: =IF(E31=0,0,G30-E31) -> 17810572149 | I31: =IF(C31="","",+C31) -> 11/03/2026 | J31: =+E31 -> 1331967 | L31: =IF(J31=0,"",L30-J31) -> 5733255864
A32: =IF(C32="","",ROW()-8) -> 24 | B32: CAS | C32: 11/03/2026 | D32: Factura V1809 | E32: 370527663 | G32: =IF(E32=0,0,G31-E32) -> 17440044486 | I32: =IF(C32="","",+C32) -> 11/03/2026 | J32: =+E32 -> 370527663 | L32: =IF(J32=0,"",L31-J32) -> 5362728201
A33: =IF(C33="","",ROW()-8) -> 25 | B33: CRUE | C33: 46128 | D33: Cuenta de cobro 419 | E33: 27568325 | G33: =IF(E33=0,0,G32-E33) -> 17412476161 | I33: =IF(C33="","",+C33) -> 46128 | J33: =+E33 -> 27568325 | L33: =IF(J33=0,"",L32-J33) -> 5335159876
A34: =IF(C34="","",ROW()-8) -> 26 | B34: CAS | C34: 46128 | D34: Cuenta de cobro 420 | E34: 13991250 | G34: =IF(E34=0,0,G33-E34) -> 17398484911 | I34: =IF(C34="","",+C34) -> 46128 | J34: =+E34 -> 13991250 | L34: =IF(J34=0,"",L33-J34) -> 5321168626 | N34: Total Recursos | O34: =SUM(O9:O33) -> 15367645700 | P34: =1-P9 -> 0.44005586 | Q34: =+F81+F83-O34 -> 12094376898
A35: =IF(C35="","",ROW()-8) -> 27 | B35: CRUE | C35: 46129 | D35: Cuenta de cobro 421 | E35: 141873578 | G35: =IF(E35=0,0,G34-E35) -> 17256611333 | I35: =IF(C35="","",+C35) -> 46129 | J35: =+E35 -> 141873578 | L35: =IF(J35=0,"",L34-J35) -> 5179295048
A36: =IF(C36="","",ROW()-8) -> 28 | B36: CAS | C36: 46129 | D36: Factura V1851 | E36: 979376728 | G36: =IF(E36=0,0,G35-E36) -> 16277234605 | I36: =IF(C36="","",+C36) -> 46129 | J36: =+E36 -> 979376728 | L36: =IF(J36=0,"",L35-J36) -> 4199918320 | O36: 1373101130
A37: =IF(C37="","",ROW()-8) -> 29 | B37: CAS | C37: 46129 | D37: Factura V1852 | E37: 1331967 | G37: =IF(E37=0,0,G36-E37) -> 16275902638 | I37: =IF(C37="","",+C37) -> 46129 | J37: =+E37 -> 1331967 | L37: =IF(J37=0,"",L36-J37) -> 4198586353
A38: =IF(C38="","",ROW()-8) -> 30 | B38: CRUE | C38: 46183 | D38: Cuenta de cobro 443 | E38: 45786710 | G38: =IF(E38=0,0,G37-E38) -> 16230115928 | I38: =IF(C38="","",+C38) -> 46183 | J38: =+E38 -> 45786710 | L38: =IF(J38=0,"",L37-J38) -> 4152799643 | O38: =+O34+O36 -> 16740746830
A39: =IF(C39="","",ROW()-8) -> 31 | B39: CRUE | C39: 46184 | D39: Factura V1938 | E39: 16130869 | G39: =IF(E39=0,0,G38-E39) -> 16213985059 | I39: =IF(C39="","",+C39) -> 46184 | J39: =+E39 -> 16130869 | L39: =IF(J39=0,"",L38-J39) -> 4136668774 | Q39: 98110087
A40: =IF(C40="","",ROW()-8) -> 32 | B40: CRUE | C40: 46183 | D40: Cuenta de cobro 448 | E40: 48935567 | G40: =IF(E40=0,0,G39-E40) -> 16165049492 | I40: =IF(C40="","",+C40) -> 46183 | J40: =+E40 -> 48935567 | L40: =IF(J40=0,"",L39-J40) -> 4087733207 | O40: 14721267575 | Q40: 164290442
A41: =IF(C41="","",ROW()-8) -> 33 | B41: CRUE | C41: 46184 | D41: Factura V1941 | E41: 4358895 | G41: =IF(E41=0,0,G40-E41) -> 16160690597 | I41: =IF(C41="","",+C41) -> 46184 | J41: =+E41 -> 4358895 | L41: =IF(J41=0,"",L40-J41) -> 4083374312 | Q41: =SUM(Q39:Q40) -> 262400529
A42: =IF(C42="","",ROW()-8) -> 34 | B42: CAS | C42: 46183 | D42: Cuenta de cobro 444 | E42: 13991250 | G42: =IF(E42=0,0,G41-E42) -> 16146699347 | I42: =IF(C42="","",+C42) -> 46183 | J42: =+E42 -> 13991250 | L42: =IF(J42=0,"",L41-J42) -> 4069383062 | O42: =+O40-O34 -> -646378125
A43: =IF(C43="","",ROW()-8) -> 35 | B43: CAS | C43: 46184 | D43: Factura V1937 | E43: 1801763757 | G43: =IF(E43=0,0,G42-E43) -> 14344935590 | I43: =IF(C43="","",+C43) -> 46184 | J43: =+E43 -> 1801763757 | L43: =IF(J43=0,"",L42-J43) -> 2267619305
A44: =IF(C44="","",ROW()-8) -> 36 | B44: CAS | C44: 46184 | D44: Factura V1939 | E44: 1331967 | G44: =IF(E44=0,0,G43-E44) -> 14343603623 | I44: =IF(C44="","",+C44) -> 46184 | J44: =+E44 -> 1331967 | L44: =IF(J44=0,"",L43-J44) -> 2266287338
A45: =IF(C45="","",ROW()-8) -> 37 | B45: CAS | C45: 46183 | D45: Cuenta de cobro 449 | E45: 13991250 | G45: =IF(E45=0,0,G44-E45) -> 14329612373 | I45: =IF(C45="","",+C45) -> 46183 | J45: =+E45 -> 13991250 | L45: =IF(J45=0,"",L44-J45) -> 2252296088 | O45: =+O42-E48 -> -680694000
A46: =IF(C46="","",ROW()-8) -> 38 | B46: CAS | C46: 46184 | D46: Factura V1940 | E46: 511655007 | G46: =IF(E46=0,0,G45-E46) -> 13817957366 | I46: =IF(C46="","",+C46) -> 46184 | J46: =+E46 -> 511655007 | L46: =IF(J46=0,"",L45-J46) -> 1740641081
A47: =IF(C47="","",ROW()-8) -> 39 | B47: CAS | C47: 46184 | D47: Factura V1942 | E47: 1331967 | G47: =IF(E47=0,0,G46-E47) -> 13816625399 | I47: =IF(C47="","",+C47) -> 46184 | J47: =+E47 -> 1331967 | L47: =IF(J47=0,"",L46-J47) -> 1739309114
A48: =IF(C48="","",ROW()-8) -> 40 | B48: CRUE | C48: 46209 | D48: Cuenta de Cobro 457 | E48: 34315875 | G48: =IF(E48=0,0,G47-E48) -> 13782309524 | I48: =IF(C48="","",+C48) -> 46209 | J48: =IF(E48=0,0,E48) -> 34315875 | L48: =IF(J48=0,"",L47-J48) -> 1704993239
A49: =IF(C49="","",ROW()-8) -> 41 | B49: CRUE | C49: 46210 | D49: Factura V1979 | E49: 4658666 | G49: =IF(E49=0,0,G48-E49) -> 13777650858 | I49: =IF(C49="","",+C49) -> 46210 | J49: =IF(E49=0,0,E49) -> 4658666 | L49: =IF(J49=0,"",L48-J49) -> 1700334573
A50: =IF(C50="","",ROW()-8) -> 42 | B50: CAS | C50: 46209 | D50: Cuenta de Cobro 456 | E50: 13991250 | G50: =IF(E50=0,0,G49-E50) -> 13763659608 | I50: =IF(C50="","",+C50) -> 46209 | J50: =IF(E50=0,0,E50) -> 13991250 | L50: =IF(J50=0,"",L49-J50) -> 1686343323
A51: =IF(C51="","",ROW()-8) -> 43 | B51: CAS | C51: 46210 | D51: Factura V1978 | E51: 511655007 | G51: =IF(E51=0,0,G50-E51) -> 13252004601 | I51: =IF(C51="","",+C51) -> 46210 | J51: =IF(E51=0,0,E51) -> 511655007 | L51: =IF(J51=0,"",L50-J51) -> 1174688316
A52: =IF(C52="","",ROW()-8) -> 44 | B52: CAS | C52: 46210 | D52: Factura V1980 | E52: 1331967 | G52: =IF(E52=0,0,G51-E52) -> 13250672634 | I52: =IF(C52="","",+C52) -> 46210 | J52: =IF(E52=0,0,E52) -> 1331967 | L52: =IF(J52=0,"",L51-J52) -> 1173356349 | N52: =+SUMIF(B9:B75,"CAS",E9:E75) -> 14551445301
A53: =IF(C53="","",ROW()-8) -> 45 | B53: CRUE | C53: 46245 | D53: Cuenta de Cobro 466 | E53: 27568325 | G53: =IF(E53=0,0,G52-E53) -> 13223104309 | I53: =IF(C53="","",+C53) -> 46245 | J53: =IF(E53=0,0,E53) -> 27568325 | L53: =IF(J53=0,"",L52-J53) -> 1145788024 | N53: =+SUMIF(B9:B75,"Crue",E9:E75) -> 354463681
A54: =IF(C54="","",ROW()-8) -> 46 | B54: CRUE | C54: 46246 | D54: Factura V2016 | E54: 3266871 | G54: =IF(E54=0,0,G53-E54) -> 13219837438 | I54: =IF(C54="","",+C54) -> 46246 | J54: =IF(E54=0,0,E54) -> 3266871 | L54: =IF(J54=0,"",L53-J54) -> 1142521153
A55: =IF(C55="","",ROW()-8) -> 47 | B55: CAS | C55: 46247 | D55: Cuenta de Cobro | E55: 13991250 | G55: =IF(E55=0,0,G54-E55) -> 13205846188 | I55: =IF(C55="","",+C55) -> 46247 | J55: =IF(E55=0,0,E55) -> 13991250 | L55: =IF(J55=0,"",L54-J55) -> 1128529903
A56: =IF(C56="","",ROW()-8) -> 48 | B56: CAS | C56: 46248 | D56: Factura V | E56: 1331967 | G56: =IF(E56=0,0,G55-E56) -> 13204514221 | I56: =IF(C56="","",+C56) -> 46248 | J56: =IF(E56=0,0,E56) -> 1331967 | L56: =IF(J56=0,"",L55-J56) -> 1127197936
A57: =IF(C57="","",ROW()-8) -> 49 | B57: CAS | C57: 46248 | D57: Factura V | E57: 665461218 | G57: =IF(E57=0,0,G56-E57) -> 12539053003 | I57: =IF(C57="","",+C57) -> 46248 | J57: =IF(E57=0,0,E57) -> 665461218 | L57: =IF(J57=0,"",L56-J57) -> 461736718
A58: =IF(C58="","",ROW()-8) | G58: =IF(E58=0,0,G57-E58) -> 0 | I58: =IF(C58="","",+C58) | J58: =IF(E58=0,0,E58) -> 0 | L58: =IF(J58=0,"",L57-J58)
A59: =IF(C59="","",ROW()-8) | G59: =IF(E59=0,0,G58-E59) -> 0 | I59: =IF(C59="","",+C59) | J59: =IF(E59=0,0,E59) -> 0 | L59: =IF(J59=0,"",L58-J59)
A60: =IF(C60="","",ROW()-8) | G60: =IF(E60=0,0,G59-E60) -> 0 | I60: =IF(C60="","",+C60) | J60: =IF(E60=0,0,E60) -> 0 | L60: =IF(J60=0,"",L59-J60)
A61: =IF(C61="","",ROW()-8) | G61: =IF(E61=0,0,G60-E61) -> 0 | I61: =IF(C61="","",+C61) | J61: =IF(E61=0,0,E61) -> 0 | L61: =IF(J61=0,"",L60-J61)
A62: =IF(C62="","",ROW()-8) | G62: =IF(E62=0,0,G61-E62) -> 0 | I62: =IF(C62="","",+C62) | J62: =IF(E62=0,0,E62) -> 0 | L62: =IF(J62=0,"",L61-J62)
A63: =IF(C63="","",ROW()-8) | G63: =IF(E63=0,0,G62-E63) -> 0 | I63: =IF(C63="","",+C63) | J63: =IF(E63=0,0,E63) -> 0 | L63: =IF(J63=0,"",L62-J63)
A64: =IF(C64="","",ROW()-8) | G64: =IF(E64=0,0,G63-E64) -> 0 | I64: =IF(C64="","",+C64) | J64: =IF(E64=0,0,E64) -> 0 | L64: =IF(J64=0,"",L63-J64)
A65: =IF(C65="","",ROW()-8) | G65: =IF(E65=0,0,G64-E65) -> 0 | I65: =IF(C65="","",+C65) | J65: =IF(E65=0,0,E65) -> 0 | L65: =IF(J65=0,"",L64-J65)
A66: =IF(C66="","",ROW()-8) | G66: =IF(E66=0,0,G65-E66) -> 0 | I66: =IF(C66="","",+C66) | J66: =IF(E66=0,0,E66) -> 0 | L66: =IF(J66=0,"",L65-J66)
A67: =IF(C67="","",ROW()-8) | G67: =IF(E67=0,0,G66-E67) -> 0 | I67: =IF(C67="","",+C67) | J67: =IF(E67=0,0,E67) -> 0 | L67: =IF(J67=0,"",L66-J67)
A68: =IF(C68="","",ROW()-8) | G68: =IF(E68=0,0,G67-E68) -> 0 | I68: =IF(C68="","",+C68) | J68: =IF(E68=0,0,E68) -> 0 | L68: =IF(J68=0,"",L67-J68)
A69: =IF(C69="","",ROW()-8) | G69: =IF(E69=0,0,G68-E69) -> 0 | I69: =IF(C69="","",+C69) | J69: =IF(E69=0,0,E69) -> 0 | L69: =IF(J69=0,"",L68-J69)
... A75: =IF(C75="","",ROW()-8) | G75: =IF(E75=0,0,G74-E75) -> 0 | I75: =IF(C75="","",+C75) | J75: =IF(E75=0,0,E75) -> 0 | L75: =IF(J75=0,"",L74-J75)
B76: Total Ejecutado | E76: =SUM(E9:E75) -> 14905908982 | F76: =1-F9 -> 0.45687996 | G76: =+F7-E76 -> 12539053003 | I76: Total Ejecutado | J76: =SUM(J9:J75) -> 14905908982 | K76: =1-K9 -> 0.030046028 | L76: =+F7-J76 -> 12539053003
B80: Fecha | E80: Aportes Fondo: IDEA + GobAnt | G80: Sin ejecución
B81: 45757 | F81: 26000000000
B82: 46020 | F82: 1300000000
B83: 46020 | F83: 1462022598
B84: 30/30/2025 | F84: 73101130
B87: Total Recursos Fondo GobAnt + IDEA | F87: =SUM(F81:G86) -> 28835123728
B88: Fecha aporte | C88: Componente | E88: Aportes realizados | G88: Sin Ejecutar
B89: 45594 | C89: Contigo Antioquia Salud - CAS | E89: 5000000000 | F89: =SUM(E89:E114)/$F$87 -> 0.53916798 | G89: =IF(E89=0,0,F87-E89) -> 23835123728
B90: 45595 | C90: Aportes en especie IDEA | E90: 1300000000 | G90: =IF(E89=0,0,G89-E90) -> 22535123728
B91: 46001 | C91: Contigo Antioquia Salud - CAS | E91: 6000000000 | G91: =IF(E90=0,0,G90-E91) -> 16535123728
B92: 46020 | C92: Aportes en especie IDEA | E92: 73101130 | G92: =IF(E91=0,0,G91-E92) -> 16462022598
B93: 46044 | C93: Contigo Antioquia Salud - CRUE | E93: 207173258 | G93: =IF(E92=0,0,G92-E93) -> 16254849340
B94: 46101 | C94: Contigo Antioquia Salud - CRUE | E94: 608644587 | G94: =IF(E93=0,0,G93-E94) -> 15646204753
B95: =+N13 -> 46171 | C95: Contigo Antioquia Salud - CAS | E95: =+O13 -> 1817086974 | G95: =IF(E94=0,0,G94-E95) -> 13829117779
B96: =+N14 -> 46191 | C96: Contigo Antioquia Salud - CAS | E96: =+O14 -> 526978224 | G96: =IF(E95=0,0,G95-E96) -> 13302139555
C97: Contigo Antioquia Salud - CAS | E97: =+J55 -> 13991250 | G97: =IF(E96=0,0,G96-E97) -> 13288148305
G98: =IF(E97=0,0,G97-E98) -> 13288148305
G99: =IF(E98=0,0,G98-E99) -> 0
G100: =IF(E99=0,0,G99-E100) -> 0
G101: =IF(E100=0,0,G100-E101) -> 0
G102: =IF(E101=0,0,G101-E102) -> 0
G103: =IF(E102=0,0,G102-E103) -> 0
G104: =IF(E103=0,0,G103-E104) -> 0
G105: =IF(E104=0,0,G104-E105) -> 0
G106: =IF(E105=0,0,G105-E106) -> 0
G107: =IF(E106=0,0,G106-E107) -> 0
G108: =IF(E107=0,0,G107-E108) -> 0
G109: =IF(E108=0,0,G108-E109) -> 0
... G114: =IF(E113=0,0,G113-E114) -> 0
B115: Aportes entregados | E115: =SUM(E89:E114) -> 15546975423 | F115: =1-F89 -> 0.46083202 | G115: =+F87-E115 -> 13288148305

Sheet % Ejecución financiera CRUE
B1: Ejecución Recursos Contigo Antioquia (CRUE) | G1: Ejecución Recursos Contigo Antioquia (CRUE)
B2: Fecha | D2: Recursos comprometidos | G2: Fecha | I2: Valor Transferido
B3: 46020 | D3: 1462022598 | G3: 46044 | I3: 207173258
G4: 46101 | I4: 608644587 | L4: =+IF('Ejecución financiera CAS'!B9="crue",'Ejecución financiera CAS'!C9,"")
B8: Valor Total Contrato | D8: =SUM(D3:E4) -> 1462022598 | G8: Total Recursos Entregados | I8: =SUM(I3:J7) -> 815817845
B9: Fecha | C9: Ejecución Financiera Valor + | E9: Sin ejecución | G9: Fecha | H9: Ejecución Financiera Valor + | J9: Sin ejecución | L9: =+C10+C11 -> 169441903 | M9: =+L9*0.08 -> 13555352 | N9: =+M9*0.19 -> 2575516.9 | O9: =+N9+M9 -> 16130869
A10: =IF(B10="","",ROW()-9) -> 1 | B10: 46128 | C10: 27568325 | D10: =+SUM(C10:C11)/$D$8 -> 0.11589554 | E10: =IF(C10=0,0,D3-C10) -> 1434454273 | G10: 12/08/2025 | H10: =+C10 -> 27568325 | I10: =SUM(H10:H11)/$I$8 -> 0.20769575 | J10: =IF(H10=0,"",I8-H10) -> 788249520
A11: =IF(B11="","",ROW()-9) -> 2 | B11: 46129 | C11: 141873578 | E11: =IF(C11=0,0,E10-C11) -> 1292580695 | G11: 02/09/2025 | H11: =+C11 -> 141873578 | J11: =IF(H11=0,"",J10-H11) -> 646375942 | L11: 45786710
A12: =IF(B12="","",ROW()-9) -> 3 | B12: 46155 | C12: 45786710 | E12: =IF(C12=0,0,E11-C12) -> 1246793985 | G12: 46155 | H12: =+C12 -> 45786710 | J12: =IF(H12=0,"",J11-H12) -> 600589232 | L12: 16130869
A13: =IF(B13="","",ROW()-9) -> 4 | B13: 46155 | C13: 16130869 | E13: =IF(C13=0,0,E12-C13) -> 1230663116 | G13: 46155 | H13: =+C13 -> 16130869 | J13: =IF(H13=0,"",J12-H13) -> 584458363 | L13: 40613589
A14: =IF(B14="","",ROW()-9) | E14: =IF(C14=0,0,E13-C14) -> 0 | G14: =IF(B14="","",+B14) | H14: =+C14 -> 0 | J14: =IF(H14=0,"",J13-H14) | L14: 4358895
A15: =IF(B15="","",ROW()-9) | E15: =IF(C15=0,0,E14-C15) -> 0 | G15: =IF(B15="","",+B15) | H15: =+C15 -> 0 | J15: =IF(H15=0,"",J14-H15) | L15: =SUM(L11:L14) -> 106890063
A16: =IF(B16="","",ROW()-9) | E16: =IF(C16=0,0,E15-C16) -> 0 | G16: =IF(B16="","",+B16) | H16: =+C16 -> 0 | J16: =IF(H16=0,"",J15-H16)
A17: =IF(B17="","",ROW()-9) | E17: =IF(C17=0,0,E16-C17) -> 0 | G17: =IF(B17="","",+B17) | H17: =+C17 -> 0 | J17: =IF(H17=0,"",J16-H17)
A18: =IF(B18="","",ROW()-9) | E18: =IF(C18=0,0,E17-C18) -> 0 | G18: =IF(B18="","",+B18) | H18: =+C18 -> 0 | J18: =IF(H18=0,"",J17-H18)
A19: =IF(B19="","",ROW()-9) | E19: =IF(C19=0,0,E18-C19) -> 0 | G19: =IF(B19="","",+B19) | H19: =+C19 -> 0 | J19: =IF(H19=0,"",J18-H19)
A20: =IF(B20="","",ROW()-9) | E20: =IF(C20=0,0,E19-C20) -> 0 | G20: =IF(B20="","",+B20) | H20: =+C20 -> 0 | J20: =IF(H20=0,"",J19-H20)
A21: =IF(B21="","",ROW()-9) | E21: =IF(C21=0,0,E20-C21) -> 0 | G21: =IF(B21="","",+B21) | H21: =+C21 -> 0 | J21: =IF(H21=0,"",J20-H21)
A22: =IF(B22="","",ROW()-9) | E22: =IF(C22=0,0,E21-C22) -> 0 | G22: =IF(B22="","",+B22) | H22: =+C22 -> 0 | J22: =IF(H22=0,"",J21-H22)
A23: =IF(B23="","",ROW()-9) | E23: =IF(C23=0,0,E22-C23) -> 0 | G23: =IF(B23="","",+B23) | H23: =+C23 -> 0 | J23: =IF(H23=0,"",J22-H23)
A24: =IF(B24="","",ROW()-9) | E24: =IF(C24=0,0,E23-C24) -> 0 | G24: =IF(B24="","",+B24) | H24: =+C24 -> 0 | J24: =IF(H24=0,"",J23-H24)
A25: =IF(B25="","",ROW()-9) | E25: =IF(C25=0,0,E24-C25) -> 0 | G25: =IF(B25="","",+B25) | H25: =+C25 -> 0 | J25: =IF(H25=0,"",J24-H25)
A26: =IF(B26="","",ROW()-9) | E26: =IF(C26=0,0,E25-C26) -> 0 | G26: =IF(B26="","",+B26) | H26: =+C26 -> 0 | J26: =IF(H26=0,"",J25-H26)
A27: =IF(B27="","",ROW()-9) | E27: =IF(C27=0,0,E26-C27) -> 0 | G27: =IF(B27="","",+B27) | H27: =+C27 -> 0 | J27: =IF(H27=0,"",J26-H27)
... A33: =IF(B33="","",ROW()-9) | E33: =IF(C33=0,0,E32-C33) -> 0 | G33: =IF(B33="","",+B33) | H33: =+C33 -> 0 | J33: =IF(H33=0,"",J32-H33)
B34: Total Ejecutado | C34: =SUM(C10:C33) -> 231359482 | D34: =1-D10 -> 0.88410446 | E34: =+D8-C34 -> 1230663116 | G34: Total Ejecutado | H34: =SUM(H10:H33) -> 231359482 | I34: =1-I10 -> 0.79230425 | J34: =+I8-H34 -> 584458363
B37: 45757 | D37: 26000000000
G39: Fecha | H39: Ejecución Financiera Fondo GobAnt + IDEA (Otrosí CRUE) | J39: Sin ejecución
G40: 46020 | H40: 1462022598 | I40: =SUM(H41:H46)/$J$40 -> 0.55800632 | J40: =+H40 -> 1462022598
G41: 46044 | H41: 207173258 | J41: =+J40-H41 -> 1254849340
G42: 46101 | H42: 608644587 | J42: =+J41-H42 -> 646204753
J43: =+J42-H43 -> 646204753
J44: =+J43-H44 -> 646204753
J45: =+J44-H45 -> 646204753
J46: =+J45-H46 -> 646204753

Sheet Ejecución Financiera CAS 1
B1: Fecha | C1: Ejecución Financiera Fondo GobAnt + IDEA (CAS) | E1: Sin ejecución | G1: Fecha | H1: Ejecución Financiera Fondo GobAnt + IDEA (Otrosí CRUE) | J1: Sin ejecución
B2: 45757 | C2: 27300000000 | D2: =SUM(C3:C8)/$C$2 -> 0.70695971 | E2: =+C2 -> 27300000000 | G2: 46020 | H2: 1462022598 | I2: =SUM(H3:H8)/$H$2 -> 0.55800632 | J2: =+H2 -> 1462022598
B3: 45594 | C3: 5000000000 | E3: =IF(C3="","",E2-C3) -> 22300000000 | G3: 46044 | H3: 207173258 | J3: =+J2-H3 -> 1254849340
B4: 45595 | C4: 1300000000 | E4: =IF(C4="","",E3-C4) -> 21000000000 | G4: 46101 | H4: 608644587 | J4: =+J3-H4 -> 646204753
B5: 46001 | C5: 6000000000 | E5: =IF(C5="","",E4-C5) -> 15000000000 | J5: =+J4-H5 -> 646204753
B6: 46118 | C6: 7000000000 | E6: =IF(C6="","",E5-C6) -> 8000000000 | J6: =+J5-H6 -> 646204753
E7: =IF(C7="","",E6-C7) | J7: =+J6-H7 -> 646204753
E8: =IF(C8="","",E7-C8) | J8: =+J7-H8 -> 646204753
B12: Fecha | C12: Ejecución Financiera Fondo GobAnt | E12: Sin ejecución
B13: 45757 | C13: 26000000000 | D13: =SUM(C14:C18)/$C$2 -> 0.65934066 | E13: =+C13 -> 26000000000
B14: 45594 | C14: 5000000000 | E14: =IF(C14="","",E13-C14) -> 21000000000
B15: 46001 | C15: 6000000000 | E15: =IF(C15="","",E14-C15) -> 15000000000
B16: 46118 | C16: 7000000000 | E16: =IF(C16="","",E15-C16) -> 8000000000
E17: =IF(C17="","",E16-C17)
E18: =IF(C18="","",E17-C18)
B23: Fecha | C23: Ejecución Financiera | E23: Sin ejecución
B24: 45757 | C24: 5000000000 | D24: =SUM(C25:C34)/$C$24 -> 0.97764798 | E24: =+C24 -> 5000000000
A25: 1 | B25: 45881 | C25: 2200000000 | E25: =IF(C25=0,0,E24-C25) -> 2800000000
A26: 2 | B26: 45902 | C26: 998095000 | E26: =IF(C26=0,0,E25-C26) -> 1801905000
A27: 3 | B27: 45915 | C27: 190754739 | E27: =IF(C27=0,0,E26-C27) -> 1611150261
A28: 4 | B28: 45940 | C28: 13650000 | E28: =IF(C28=0,0,E27-C28) -> 1597500261
A29: 5 | B29: 45945 | C29: 95018644 | E29: =IF(C29=0,0,E28-C29) -> 1502481617
A30: 6 | B30: 45947 | C30: 730635725 | E30: =IF(C30=0,0,E29-C30) -> 771845892
A31: 7 | B31: 45947 | C31: 211478886 | E31: =IF(C31=0,0,E30-C31) -> 560367006
A32: 8 | B32: 45985 | C32: 13650000 | E32: =IF(C32=0,0,E31-C32) -> 546717006
A33: 9 | B33: 45985 | C33: 70856001 | E33: =IF(C33=0,0,E32-C33) -> 475861005
A34: 10 | B34: 45985 | C34: 364100919 | E34: =IF(C34=0,0,E33-C34) -> 111760086
E35: =IF(C35=0,0,E34-C35) -> 0
B36: Total Ejecutado | C36: =SUM(C25:C35) -> 4888239914 | D36: =1-D24 -> 0.022352017 | E36: =+C24-C36 -> 111760086
B40: Fecha | C40: Ejecución Financiera | E40: Sin ejecución
B41: 45985 | C41: =+E34 -> 111760086 | D41: =+SUM(C43:C71)/E42 -> 0.99993741 | E41: =+C41 -> 111760086
B42: 46001 | C42: 6000000000 | E42: =+E41+C42 -> 6111760086
B43: 02/12/2025 | C43: 13650000 | E43: =IF(C43=0,0,E42-C43) -> 6098110086
B44: 02/12/2025 | C44: 1095953586 | E44: =IF(C44=0,0,E43-C44) -> 5002156500
B45: 03/12/2025 | C45: 1299480 | E45: =IF(C45=0,0,E44-C45) -> 5000857020
B46: 03/12/2025 | C46: 262400529 | E46: =IF(C46=0,0,E45-C46) -> 4738456491
B47: 16/01/2026 | C47: 1539588229 | E47: =IF(C47=0,0,E46-C47) -> 3198868262
B48: 19/01/2026 | C48: 105634262 | E48: =IF(C48=0,0,E47-C48) -> 3093234000
B49: 19/01/2026 | C49: 378854365 | E49: =IF(C49=0,0,E48-C49) -> 2714379635
B50: 16/01/2026 | C50: 13650000 | E50: =IF(C50=0,0,E49-C50) -> 2700729635
B51: 10/02/2026 | C51: 1157936725 | E51: =IF(C51=0,0,E50-C51) -> 1542792910
B52: 10/02/2026 | C52: 147868279 | E52: =IF(C52=0,0,E51-C52) -> 1394924631
B53: 10/02/2026 | C53: 13991250 | E53: =IF(C53=0,0,E52-C53) -> 1380933381
B54: 10/03/2026 | C54: 13991250 | E54: =IF(C54=0,0,E53-C54) -> 1366942131
... B56: 11/03/2026 | C56: 370527663 | E56: =IF(C56=0,0,E55-C56) -> 995082501
B57: 46128 | C57: 13991250 | E57: =IF(C57=0,0,E56-C57) -> 981091251
B58: 46129 | C58: 979376728 | E58: =IF(C58=0,0,E57-C58) -> 1714523
B59: 46129 | C59: 1331967 | E59: =IF(C59=0,0,E58-C59) -> 382556
E60: =IF(C60=0,0,E59-C60) -> 0
E61: =IF(C61=0,0,E60-C61) -> 0
E62: =IF(C62=0,0,E61-C62) -> 0
E63: =IF(C63=0,0,E62-C63) -> 0
E64: =IF(C64=0,0,E63-C64) -> 0
E65: =IF(C65=0,0,E64-C65) -> 0
E66: =IF(C66=0,0,E65-C66) -> 0
E67: =IF(C67=0,0,E66-C67) -> 0
E68: =IF(C68=0,0,E67-C68) -> 0
E69: =IF(C69=0,0,E68-C69) -> 0
E70: =IF(C70=0,0,E69-C70) -> 0
E71: =IF(C71=0,0,E70-C71) -> 0
B72: Total Ejecutado | C72: =SUM(C43:C71) -> 6111377530 | D72: =1-D41 -> 6.2593426e-05 | E72: =+E42-C72 -> 382556
B77: Fecha | C77: Ejecución Financiera | E77: Sin ejecución
B78: =+B59 -> 46129 | C78: =+E72 -> 382556 | D78: =+SUM(C80:C90)/E79 -> 0.33484816 | E78: =+C78 -> 382556
B79: Mayo | C79: 7000000000 | E79: =+E78+C79 -> 7000382556
B80: 46155 | C80: 13991250 | E80: =IF(C80=0,0,E79-C80) -> 6986391306
B81: 46155 | C81: 1331967 | E81: =IF(C81=0,0,E80-C81) -> 6985059339
B82: 46155 | C82: 1801763757 | E82: =IF(C82=0,0,E81-C82) -> 5183295582
B83: =+'Ejecución financiera CAS'!N14 -> 46191 | C83: =+'Ejecución financiera CAS'!O14 -> 526978224 | E83: =IF(C83=0,0,E82-C83) -> 4656317358
E84: =IF(C84=0,0,E83-C84) -> 0
E85: =IF(C85=0,0,E84-C85) -> 0
E86: =IF(C86=0,0,E85-C86) -> 0
E87: =IF(C87=0,0,E86-C87) -> 0
E88: =IF(C88=0,0,E87-C88) -> 0
E89: =IF(C89=0,0,E88-C89) -> 0
E90: =IF(C90=0,0,E89-C90) -> 0
B91: Total Ejecutado | C91: =SUM(C80:C90) -> 2344065198 | D91: =1-D78 -> 0.66515184 | E91: =+E79-C91 -> 4656317358

Sheet Avance mensual Conv IDEA
A1: Fecha informe | B1: # | C1: Ejecución | D1: Total informes | E1: 38
A2: 45626 | B2: 1 | C2: =+B2/$E$1 -> 0.026315789
A3: 45657 | B3: 2 | C3: =+B3/$E$1 -> 0.052631579
A4: 45688 | B4: 3 | C4: =+B4/$E$1 -> 0.078947368
A5: 45716 | B5: 4 | C5: =+B5/$E$1 -> 0.10526316
A6: 45747 | B6: 5 | C6: =+B6/$E$1 -> 0.13157895
A7: 45777 | B7: 6 | C7: =+B7/$E$1 -> 0.15789474
A8: 45808 | B8: 7 | C8: =+B8/$E$1 -> 0.18421053
A9: 45838 | B9: 8 | C9: =+B9/$E$1 -> 0.21052632
A10: 45869 | B10: 9 | C10: =+B10/$E$1 -> 0.23684211
A11: 45900 | B11: 10 | C11: =+B11/$E$1 -> 0.26315789
A12: 45930 | B12: 11 | C12: =+B12/$E$1 -> 0.28947368
A13: 45961 | B13: 12 | C13: =+B13/$E$1 -> 0.31578947
... A21: 46203 | B21: 20 | C21: =+B21/$E$1 -> 0.52631579
A22: 46234 | B22: 21 | C22: =+B22/$E$1 -> 0.55263158 | E22: =+C22-C19 -> 0.078947368
A23: 46265 | B23: 22 | C23: =+B23/$E$1 -> 0.57894737
A24: 46295 | B24: 23 | C24: =+B24/$E$1 -> 0.60526316
A25: 46326 | B25: 24 | C25: =+B25/$E$1 -> 0.63157895
A26: 46356 | B26: 25 | C26: =+B26/$E$1 -> 0.65789474
A27: 46387 | B27: 26 | C27: =+B27/$E$1 -> 0.68421053
A28: 46418 | B28: 27 | C28: =+B28/$E$1 -> 0.71052632
A29: 46446 | B29: 28 | C29: =+B29/$E$1 -> 0.73684211
A30: 46477 | B30: 29 | C30: =+B30/$E$1 -> 0.76315789
A31: 46507 | B31: 30 | C31: =+B31/$E$1 -> 0.78947368
A32: 46538 | B32: 31 | C32: =+B32/$E$1 -> 0.81578947
A33: 46568 | B33: 32 | C33: =+B33/$E$1 -> 0.84210526
A34: 46599 | B34: 33 | C34: =+B34/$E$1 -> 0.86842105
... A39: 46752 | B39: 38 | C39: =+B39/$E$1 -> 1

Sheet Hoja1
C1: Recursos vigencia 2026
D2: 7000000000
C4: Fecha | D4: Recuros Transferidos
C5: 46171 | D5: 1817086974
C6: 46191 | D6: 526978224
C7: 46220 | D7: 526978224
C8: Total | D8: =SUM(D5:D7) -> 2871043422
C10: Recuros por transferir:
D11: =7000000000-SUM(D5:D7) -> 4128956578
